libcasm/include/casm/crystallography/Adapter.hh
libcasm/include/casm/crystallography/AnisoValTraits.hh
libcasm/include/casm/crystallography/BasicStructure.hh
libcasm/include/casm/crystallography/BasicStructureTools.hh
libcasm/include/casm/crystallography/CanonicalForm.hh
libcasm/include/casm/crystallography/Coordinate.hh
libcasm/include/casm/crystallography/CoordinateSystems.hh
libcasm/include/casm/crystallography/DoFDecl.hh
libcasm/include/casm/crystallography/DoFSet.hh
libcasm/include/casm/crystallography/HermiteCounter.hh
libcasm/include/casm/crystallography/IntegralCoordinateWithin.hh
libcasm/include/casm/crystallography/Lattice.hh
libcasm/include/casm/crystallography/LatticeIsEquivalent.hh
libcasm/include/casm/crystallography/LatticeMap.hh
libcasm/include/casm/crystallography/LinearIndexConverter.hh
libcasm/include/casm/crystallography/Molecule.hh
libcasm/include/casm/crystallography/Niggli.hh
libcasm/include/casm/crystallography/OccupantDoFIsEquivalent.hh
libcasm/include/casm/crystallography/SimpleStrucMapCalculator.hh
libcasm/include/casm/crystallography/SimpleStructure.hh
libcasm/include/casm/crystallography/SimpleStructureTools.hh
libcasm/include/casm/crystallography/Site.hh
libcasm/include/casm/crystallography/SpeciesProperty.hh
libcasm/include/casm/crystallography/Strain.hh
libcasm/include/casm/crystallography/StrainConverter.hh
libcasm/include/casm/crystallography/StrucMapCalculatorInterface.hh
libcasm/include/casm/crystallography/StrucMapping.hh
libcasm/include/casm/crystallography/Superlattice.hh
libcasm/include/casm/crystallography/SuperlatticeEnumerator.hh
libcasm/include/casm/crystallography/SymInfo.hh
libcasm/include/casm/crystallography/SymRepBuilder.hh
libcasm/include/casm/crystallography/SymTools.hh
libcasm/include/casm/crystallography/SymType.hh
libcasm/include/casm/crystallography/SymTypeComparator.hh
libcasm/include/casm/crystallography/UnitCellCoord.hh
libcasm/include/casm/crystallography/UnitCellCoordRep.hh
libcasm_xtal-2.3.0.dist-info/licenses/LICENSE
libcasm_xtal-2.3.0.dist-info/METADATA
libcasm_xtal-2.3.0.dist-info/WHEEL
libcasm_xtal-2.3.0.dist-info/top_level.txt
libcasm_xtal-2.3.0.dist-info/RECORD
