Metadata-Version: 2.4
Name: libcasm-xtal
Version: 2.3.0
Summary: CASM crystallography
Author-email: CASM developers <casm-developers@lists.engr.ucsb.edu>
License-Expression: LGPL-2.1-or-later
Project-URL: Homepage, https://prisms-center.github.io/CASMcode_docs/
Project-URL: Repository, https://github.com/prisms-center/CASMcode_crystallography
Classifier: Development Status :: 5 - Production/Stable
Classifier: Programming Language :: Python :: 3
Classifier: Programming Language :: C++
Classifier: Topic :: Scientific/Engineering
Requires-Python: <3.15,>=3.10
License-File: LICENSE
Requires-Dist: libcasm-global>=2.3.0
Requires-Dist: numpy
Dynamic: license-file
